Metadata-Version: 2.1
Name: kmeans-to-pyLDAvis
Version: 0.1.1
Summary: Gaussian and Binomial distributions
Author-email: behi.rabiei@gmail.com
License: UNKNOWN
Platform: UNKNOWN
